{
	"display": {
		"icon": {
			"item": "minecraft:iron_axe"
		},
		"title": "Timber                           ",
		"description": ["",{"text":"Trees can be instantly chopped with any axe in survival mode.\n","color":"gold"},{"text":"Enter","color":"green"},{"text":" ","color":"gold"},{"text":"/trigger TimberToggle","color":"yellow"},{"text":" to toggle the datapack on or off.\n","color":"gold"},{"text":"Enter","color":"green"},{"text":" ","color":"gold"},{"text":"/function timber:help","color":"yellow"},{"text":" for config options.","color":"gold"}],
		"show_toast": false,
		"announce_to_chat": false
	},
    "parent": "vanillatweaks:root",
	"criteria": {
		"tick": {
			"trigger": "minecraft:tick"
		}
	}
}
